{
	"configurations" : 
	[
		{
			"directories" : 
			[
				{
					"build" : ".",
					"jsonFile" : "directory-.-Debug-f5ebdc15457944623624.json",
					"minimumCMakeVersion" : 
					{
						"string" : "3.26"
					},
					"projectIndex" : 0,
					"source" : ".",
					"targetIndexes" : 
					[
						0
					]
				}
			],
			"name" : "Debug",
			"projects" : 
			[
				{
					"directoryIndexes" : 
					[
						0
					],
					"name" : "labAS5",
					"targetIndexes" : 
					[
						0
					]
				}
			],
			"targets" : 
			[
				{
					"directoryIndex" : 0,
					"id" : "labAS5::@6890427a1f51a3e7e1df",
					"jsonFile" : "target-labAS5-Debug-5a86fff709e8b177a1c4.json",
					"name" : "labAS5",
					"projectIndex" : 0
				}
			]
		}
	],
	"kind" : "codemodel",
	"paths" : 
	{
		"build" : "/Users/lucas/CLionProjects/ALG/labAS5/cmake-build-debug",
		"source" : "/Users/lucas/CLionProjects/ALG/labAS5"
	},
	"version" : 
	{
		"major" : 2,
		"minor" : 5
	}
}
